{
	"name": "ds_getMeatdata_source_adls",
	"properties": {
		"linkedServiceName": {
			"referenceName": "ls_source_adls_gen2",
			"type": "LinkedServiceReference"
		},
		"annotations": [],
		"type": "DelimitedText",
		"typeProperties": {
			"location": {
				"type": "AzureBlobFSLocation",
				"folderPath": "source",
				"fileSystem": "sourcegen2container"
			},
			"columnDelimiter": ",",
			"escapeChar": "\\",
			"firstRowAsHeader": false,
			"quoteChar": "\""
		},
		"schema": []
	},
	"type": "Microsoft.DataFactory/factories/datasets"
}